nornir_jinja2/__init__.py
nornir_jinja2/plugins/__init__.py
nornir_jinja2/plugins/tasks/__init__.py
nornir_jinja2/plugins/tasks/template_file.py
nornir_jinja2/plugins/tasks/template_string.py
nornir_jinja2-0.1.2.dist-info/LICENSE
nornir_jinja2-0.1.2.dist-info/WHEEL
nornir_jinja2-0.1.2.dist-info/METADATA
nornir_jinja2-0.1.2.dist-info/RECORD
